chat/__init__.py
chat/admin.py
chat/apps.py
chat/models.py
chat/tests.py
chat/urls.py
chat/views.py
chat/templates/home.html
chat/templates/room.html
djangochat/__init__.py
djangochat/asgi.py
djangochat/settings.py
djangochat/urls.py
djangochat/wsgi.py
mychat_app-1.0.0.dist-info/METADATA
mychat_app-1.0.0.dist-info/WHEEL
mychat_app-1.0.0.dist-info/top_level.txt
mychat_app-1.0.0.dist-info/RECORD
