Metadata-Version: 2.1
Name: mychat-app
Version: 1.0.0
Summary: Simple chat application using django
